CHANGES.rst
LICENSE
MANIFEST.in
README.rst
manage.py
setup.cfg
setup.py
jsonfield/__init__.py
jsonfield/apps.py
jsonfield/encoder.py
jsonfield/fields.py
jsonfield/models.py
jsonfield/subclassing.py
jsonfield_joinup.egg-info/PKG-INFO
jsonfield_joinup.egg-info/SOURCES.txt
jsonfield_joinup.egg-info/dependency_links.txt
jsonfield_joinup.egg-info/requires.txt
jsonfield_joinup.egg-info/top_level.txt