Metadata-Version: 1.1
Name: jsonfield-joinup
Version: 2.1.2
Summary: A reusable Django field that allows you to store validated JSON in your model.
Home-page: https://github.com/we-are-Joinup/jsonfield
Author: Joinup
Author-email: desarrollo@joinup.es
License: MIT
Platform: UNKNOWN
Classifier: Environment :: Web Environment
Classifier: Intended Audience :: Developers
Classifier: Operating System :: OS Independent
Classifier: Programming Language :: Python
Classifier: Programming Language :: Python :: 2.7
Classifier: Programming Language :: Python :: 3
Classifier: Programming Language :: Python :: 3.6
Classifier: Programming Language :: Python :: 3.7
Classifier: Programming Language :: Python :: 3.8
Classifier: Framework :: Django
